pybd_base/__init__.py
pybd_base/base.py
pybd_base-1.0.2.dist-info/METADATA
pybd_base-1.0.2.dist-info/WHEEL
pybd_base-1.0.2.dist-info/top_level.txt
pybd_base-1.0.2.dist-info/RECORD
